{
 "headerInfo": { "formFields": {} },
 "benificiary": {
  "Label": "benificiary",
  "formFields": {
   "PN_GUARDIAN_NAME": {
    "PFD_HINT": "Guardian Name",
    "PFD_FORM_ITEM_TYPE1": "TYPE",
    "PFD_COLUMN_NAME": "PN_GUARDIAN_NAME",
    "PFD_FORM_ITEM_TYPE2": "benificiary",
    "PFD_TABLE_NAME": "LT_POL_NOMINEE",
    "PFD_DATA_TYPE": "text",
    "PFD_SYS_ID": 118,
    "PFD_VALIDATION_ID": "1",
    "PFD_MINMAX_YN": false,
    "PFD_FLD_VALUE": "",
    "PFD_DFLT_VALUE_YN": "0",
    "PFD_SEQ_NO": 11,
    "PFD_CLASS_NAME": "CLASS",
    "PFD_VALIDATION_YN": "1",
    "PFD_MANDATORY_YN": true,
    "PFD_EDIT_YN": "1",
    "PFD_FLD_NAME": "GUARDIAN NAME",
    "PFD_RADIO_GRP_NAME": "GROUP",
    "PFD_PROG_CODE": "QUOTATIONENTRY",
    "PFD_FONT_SIZE": "20",
    "PFD_FLD_LEN": "25",
    "PFD_HIDE_YN": "1",
    "PFD_SCREEN_NAME": "QUOTATIONENTRY"
   },
   "PN_NOM_TYPE": {
    "PFD_HINT": "Type",
    "PFD_FORM_ITEM_TYPE1": "TYPE",
    "PFD_COLUMN_NAME": "PN_NOM_TYPE",
    "PFD_FORM_ITEM_TYPE2": "benificiary",
    "PFD_TABLE_NAME": "LT_POL_NOMINEE",
    "PFD_DATA_TYPE": "codedesc",
    "PFD_SYS_ID": 109,
    "PFD_VALIDATION_ID": "1",
    "PFD_MINMAX_YN": false,
    "PFD_FLD_VALUE": "",
    "PFD_DFLT_VALUE_YN": "0",
    "PFD_SEQ_NO": 2,
    "PFD_CLASS_NAME": "CLASS",
    "PFD_VALIDATION_YN": "1",
    "PFD_MANDATORY_YN": true,
    "PFD_EDIT_YN": "1",
    "PFD_FLD_NAME": "TYPE",
    "PFD_RADIO_GRP_NAME": "GROUP",
    "PFD_PROG_CODE": "QUOTATIONENTRY",
    "PFD_FONT_SIZE": "20",
    "PFD_FLD_LEN": "25",
    "PFD_HIDE_YN": "1",
    "PFD_SCREEN_NAME": "QUOTATIONENTRY"
   },
   "PN_AGE": {
    "PFD_HINT": "Age",
    "PFD_FORM_ITEM_TYPE1": "TYPE",
    "PFD_COLUMN_NAME": "PN_AGE",
    "PFD_FORM_ITEM_TYPE2": "benificiary",
    "PFD_TABLE_NAME": "LT_POL_NOMINEE",
    "PFD_DATA_TYPE": "number",
    "PFD_SYS_ID": 114,
    "PFD_VALIDATION_ID": "1",
    "PFD_MINMAX_YN": false,
    "PFD_FLD_VALUE": "",
    "PFD_DFLT_VALUE_YN": "0",
    "PFD_SEQ_NO": 7,
    "PFD_CLASS_NAME": "CLASS",
    "PFD_VALIDATION_YN": "1",
    "PFD_MANDATORY_YN": true,
    "PFD_EDIT_YN": "1",
    "PFD_FLD_NAME": "AGE",
    "PFD_RADIO_GRP_NAME": "GROUP",
    "PFD_PROG_CODE": "QUOTATIONENTRY",
    "PFD_FONT_SIZE": "20",
    "PFD_FLD_LEN": "25",
    "PFD_HIDE_YN": "1",
    "PFD_SCREEN_NAME": "QUOTATIONENTRY"
   },
   "PN_NOM_NAME": {
    "PFD_HINT": "text",
    "PFD_FORM_ITEM_TYPE1": "TYPE",
    "PFD_COLUMN_NAME": "PN_NOM_NAME",
    "PFD_FORM_ITEM_TYPE2": "benificiary",
    "PFD_TABLE_NAME": "LT_POL_NOMINEE",
    "PFD_DATA_TYPE": "text",
    "PFD_SYS_ID": 112,
    "PFD_VALIDATION_ID": "1",
    "PFD_MINMAX_YN": false,
    "PFD_FLD_VALUE": "",
    "PFD_DFLT_VALUE_YN": "0",
    "PFD_SEQ_NO": 5,
    "PFD_CLASS_NAME": "CLASS",
    "PFD_VALIDATION_YN": "1",
    "PFD_MANDATORY_YN": true,
    "PFD_EDIT_YN": "1",
    "PFD_FLD_NAME": "BENEFICIARY NAME",
    "PFD_RADIO_GRP_NAME": "GROUP",
    "PFD_PROG_CODE": "QUOTATIONENTRY",
    "PFD_FONT_SIZE": "20",
    "PFD_FLD_LEN": "25",
    "PFD_HIDE_YN": "1",
    "PFD_SCREEN_NAME": "QUOTATIONENTRY"
   },
   "PN_SR_NO": {
    "PFD_HINT": "Serial Number",
    "PFD_FORM_ITEM_TYPE1": "TYPE",
    "PFD_COLUMN_NAME": "PN_SR_NO",
    "PFD_FORM_ITEM_TYPE2": "benificiary",
    "PFD_TABLE_NAME": "LT_POL_NOMINEE",
    "PFD_DATA_TYPE": "text",
    "PFD_SYS_ID": 108,
    "PFD_VALIDATION_ID": "1",
    "PFD_MINMAX_YN": false,
    "PFD_FLD_VALUE": "",
    "PFD_DFLT_VALUE_YN": "0",
    "PFD_SEQ_NO": 1,
    "PFD_CLASS_NAME": "CLASS",
    "PFD_VALIDATION_YN": "1",
    "PFD_MANDATORY_YN": true,
    "PFD_EDIT_YN": "1",
    "PFD_FLD_NAME": "SR.NO",
    "PFD_RADIO_GRP_NAME": "GROUP",
    "PFD_PROG_CODE": "QUOTATIONENTRY",
    "PFD_FONT_SIZE": "20",
    "PFD_FLD_LEN": "25",
    "PFD_HIDE_YN": "1",
    "PFD_SCREEN_NAME": "QUOTATIONENTRY"
   },
   "PN_RELATION": {
    "PFD_HINT": "Relation Code",
    "PFD_FORM_ITEM_TYPE1": "TYPE",
    "PFD_COLUMN_NAME": "PN_RELATION",
    "PFD_FORM_ITEM_TYPE2": "benificiary",
    "PFD_TABLE_NAME": "LT_POL_NOMINEE",
    "PFD_DATA_TYPE": "codedesc",
    "PFD_SYS_ID": 116,
    "PFD_VALIDATION_ID": "1",
    "PFD_MINMAX_YN": false,
    "PFD_FLD_VALUE": "",
    "PFD_DFLT_VALUE_YN": "0",
    "PFD_SEQ_NO": 9,
    "PFD_CLASS_NAME": "CLASS",
    "PFD_VALIDATION_YN": "1",
    "PFD_MANDATORY_YN": true,
    "PFD_EDIT_YN": "1",
    "PFD_FLD_NAME": "RALETION CODE ",
    "PFD_RADIO_GRP_NAME": "GROUP",
    "PFD_PROG_CODE": "QUOTATIONENTRY",
    "PFD_FONT_SIZE": "20",
    "PFD_FLD_LEN": "25",
    "PFD_HIDE_YN": "1",
    "PFD_SCREEN_NAME": "QUOTATIONENTRY"
   },
   "PN_PERC": {
    "PFD_HINT": "Percentage",
    "PFD_FORM_ITEM_TYPE1": "TYPE",
    "PFD_COLUMN_NAME": "PN_PERC",
    "PFD_FORM_ITEM_TYPE2": "benificiary",
    "PFD_TABLE_NAME": "LT_POL_NOMINEE",
    "PFD_DATA_TYPE": "text",
    "PFD_SYS_ID": 117,
    "PFD_VALIDATION_ID": "1",
    "PFD_MINMAX_YN": false,
    "PFD_FLD_VALUE": "",
    "PFD_DFLT_VALUE_YN": "0",
    "PFD_SEQ_NO": 10,
    "PFD_CLASS_NAME": "CLASS",
    "PFD_VALIDATION_YN": "1",
    "PFD_MANDATORY_YN": true,
    "PFD_EDIT_YN": "1",
    "PFD_FLD_NAME": "PERCENTAGE",
    "PFD_RADIO_GRP_NAME": "GROUP",
    "PFD_PROG_CODE": "QUOTATIONENTRY",
    "PFD_FONT_SIZE": "20",
    "PFD_FLD_LEN": "25",
    "PFD_HIDE_YN": "1",
    "PFD_SCREEN_NAME": "QUOTATIONENTRY"
   },
   "PN_CATG_CODE": {
    "PFD_HINT": "Gender",
    "PFD_FORM_ITEM_TYPE1": "TYPE",
    "PFD_COLUMN_NAME": "PN_CATG_CODE",
    "PFD_FORM_ITEM_TYPE2": "benificiary",
    "PFD_TABLE_NAME": "LT_POL_NOMINEE",
    "PFD_DATA_TYPE": "codedesc",
    "PFD_SYS_ID": 115,
    "PFD_VALIDATION_ID": "1",
    "PFD_MINMAX_YN": false,
    "PFD_FLD_VALUE": "",
    "PFD_DFLT_VALUE_YN": "0",
    "PFD_SEQ_NO": 8,
    "PFD_CLASS_NAME": "CLASS",
    "PFD_VALIDATION_YN": "1",
    "PFD_MANDATORY_YN": true,
    "PFD_EDIT_YN": "1",
    "PFD_FLD_NAME": "GENDER",
    "PFD_RADIO_GRP_NAME": "GROUP",
    "PFD_PROG_CODE": "QUOTATIONENTRY",
    "PFD_FONT_SIZE": "20",
    "PFD_FLD_LEN": "25",
    "PFD_HIDE_YN": "1",
    "PFD_SCREEN_NAME": "QUOTATIONENTRY"
   },
   "PN_NOM_ID_TYPE": {
    "PFD_HINT": "No ID Type",
    "PFD_FORM_ITEM_TYPE1": "TYPE",
    "PFD_COLUMN_NAME": "PN_NOM_ID_TYPE",
    "PFD_FORM_ITEM_TYPE2": "benificiary",
    "PFD_TABLE_NAME": "LT_POL_NOMINEE",
    "PFD_DATA_TYPE": "lov",
    "PFD_SYS_ID": 110,
    "PFD_VALIDATION_ID": "1",
    "PFD_MINMAX_YN": false,
    "PFD_FLD_VALUE": "",
    "PFD_DFLT_VALUE_YN": "0",
    "PFD_SEQ_NO": 3,
    "PFD_CLASS_NAME": "CLASS",
    "PFD_VALIDATION_YN": "1",
    "PFD_MANDATORY_YN": true,
    "PFD_EDIT_YN": "1",
    "PFD_FLD_NAME": "BENEFICIARY ID TYPE",
    "PFD_RADIO_GRP_NAME": "GROUP",
    "PFD_PROG_CODE": "QUOTATIONENTRY",
    "PFD_FONT_SIZE": "20",
    "PFD_FLD_LEN": "25",
    "PFD_HIDE_YN": "1",
    "PFD_SCREEN_NAME": "QUOTATIONENTRY"
   },
   "PN_DOB": {
    "PFD_HINT": "D.O.B.",
    "PFD_FORM_ITEM_TYPE1": "TYPE",
    "PFD_COLUMN_NAME": "PN_DOB",
    "PFD_FORM_ITEM_TYPE2": "benificiary",
    "PFD_TABLE_NAME": "LT_POL_NOMINEE",
    "PFD_DATA_TYPE": "date",
    "PFD_SYS_ID": 113,
    "PFD_VALIDATION_ID": "1",
    "PFD_MINMAX_YN": false,
    "PFD_FLD_VALUE": "",
    "PFD_DFLT_VALUE_YN": "0",
    "PFD_SEQ_NO": 6,
    "PFD_CLASS_NAME": "CLASS",
    "PFD_VALIDATION_YN": "1",
    "PFD_MANDATORY_YN": true,
    "PFD_EDIT_YN": "1",
    "PFD_FLD_NAME": "DOB",
    "PFD_RADIO_GRP_NAME": "GROUP",
    "PFD_PROG_CODE": "QUOTATIONENTRY",
    "PFD_FONT_SIZE": "20",
    "PFD_FLD_LEN": "25",
    "PFD_HIDE_YN": "1",
    "PFD_SCREEN_NAME": "QUOTATIONENTRY"
   },
   "PN_MOBILE_NO": {
    "PFD_HINT": "Phone Number",
    "PFD_FORM_ITEM_TYPE1": "TYPE",
    "PFD_COLUMN_NAME": "PN_MOBILE_NO",
    "PFD_FORM_ITEM_TYPE2": "benificiary",
    "PFD_TABLE_NAME": "LT_POL_NOMINEE",
    "PFD_DATA_TYPE": "phonenumber",
    "PFD_SYS_ID": 119,
    "PFD_VALIDATION_ID": "1",
    "PFD_MINMAX_YN": false,
    "PFD_FLD_VALUE": "",
    "PFD_DFLT_VALUE_YN": "0",
    "PFD_SEQ_NO": 12,
    "PFD_CLASS_NAME": "CLASS",
    "PFD_VALIDATION_YN": "1",
    "PFD_MANDATORY_YN": true,
    "PFD_EDIT_YN": "1",
    "PFD_FLD_NAME": "GUARDIAN MOBILE NO",
    "PFD_RADIO_GRP_NAME": "GROUP",
    "PFD_PROG_CODE": "QUOTATIONENTRY",
    "PFD_FONT_SIZE": "20",
    "PFD_FLD_LEN": "25",
    "PFD_HIDE_YN": "1",
    "PFD_SCREEN_NAME": "QUOTATIONENTRY"
   }
  }
 },
 "staticDetails": { "formFields": {} },
 "mrvListingId": [
  { "queryName": "Life Assured Details", "queryId": "22" },
  { "queryName": "Benificiary", "queryId": "23" },
  { "queryName": "chargs_dis-load_Conditions", "queryId": "24" },
  { "queryName": "CheckList", "queryId": "25" },
  {
   "queryName": "comments_maturity_remainder_dispatch details",
   "queryId": "26"
  }
 ],
 "life_assured_details": {
  "Label": "life_assured_details",
  "formFields": {
   "PAD_OCC_CODE": {
    "PFD_HINT": "Occ Code",
    "PFD_FORM_ITEM_TYPE1": "TYPE",
    "PFD_COLUMN_NAME": "PAD_OCC_CODE",
    "PFD_FORM_ITEM_TYPE2": "life_assured_details",
    "PFD_TABLE_NAME": "LT_POL_ASSURED_DET",
    "PFD_DATA_TYPE": "codedesc",
    "PFD_SYS_ID": 92,
    "PFD_VALIDATION_ID": "1",
    "PFD_MINMAX_YN": false,
    "PFD_FLD_VALUE": "",
    "PFD_DFLT_VALUE_YN": "0",
    "PFD_SEQ_NO": 13,
    "PFD_CLASS_NAME": "CLASS",
    "PFD_VALIDATION_YN": "1",
    "PFD_MANDATORY_YN": true,
    "PFD_EDIT_YN": "1",
    "PFD_FLD_NAME": "OCCUPATION CODE",
    "PFD_RADIO_GRP_NAME": "GROUP",
    "PFD_PROG_CODE": "QUOTATIONENTRY",
    "PFD_FONT_SIZE": "20",
    "PFD_FLD_LEN": "25",
    "PFD_HIDE_YN": "1",
    "PFD_SCREEN_NAME": "QUOTATIONENTRY"
   },
   "PAD_OCC_CLASS": {
    "PFD_HINT": "Occ Class",
    "PFD_FORM_ITEM_TYPE1": "TYPE",
    "PFD_COLUMN_NAME": "PAD_OCC_CLASS",
    "PFD_FORM_ITEM_TYPE2": "life_assured_details",
    "PFD_TABLE_NAME": "LT_POL_ASSURED_DET",
    "PFD_DATA_TYPE": "codedesc",
    "PFD_SYS_ID": 93,
    "PFD_VALIDATION_ID": "1",
    "PFD_MINMAX_YN": false,
    "PFD_FLD_VALUE": "",
    "PFD_DFLT_VALUE_YN": "0",
    "PFD_SEQ_NO": 14,
    "PFD_CLASS_NAME": "CLASS",
    "PFD_VALIDATION_YN": "1",
    "PFD_MANDATORY_YN": true,
    "PFD_EDIT_YN": "1",
    "PFD_FLD_NAME": "OCCUPATION CLASS",
    "PFD_RADIO_GRP_NAME": "GROUP",
    "PFD_PROG_CODE": "QUOTATIONENTRY",
    "PFD_FONT_SIZE": "20",
    "PFD_FLD_LEN": "25",
    "PFD_HIDE_YN": "1",
    "PFD_SCREEN_NAME": "QUOTATIONENTRY"
   },
   "PAD_GENDER": {
    "PFD_HINT": "Gender",
    "PFD_FORM_ITEM_TYPE1": "TYPE",
    "PFD_COLUMN_NAME": "PAD_GENDER",
    "PFD_FORM_ITEM_TYPE2": "life_assured_details",
    "PFD_TABLE_NAME": "LT_POL_ASSURED_DET",
    "PFD_DATA_TYPE": "text",
    "PFD_SYS_ID": 84,
    "PFD_VALIDATION_ID": "1",
    "PFD_MINMAX_YN": false,
    "PFD_FLD_VALUE": "",
    "PFD_DFLT_VALUE_YN": "0",
    "PFD_SEQ_NO": 5,
    "PFD_CLASS_NAME": "CLASS",
    "PFD_VALIDATION_YN": "1",
    "PFD_MANDATORY_YN": true,
    "PFD_EDIT_YN": "1",
    "PFD_FLD_NAME": "GENDER",
    "PFD_RADIO_GRP_NAME": "GROUP",
    "PFD_PROG_CODE": "QUOTATIONENTRY",
    "PFD_FONT_SIZE": "20",
    "PFD_FLD_LEN": "25",
    "PFD_HIDE_YN": "1",
    "PFD_SCREEN_NAME": "QUOTATIONENTRY"
   },
   "PAD_AGE_PROOF_FLAG": {
    "PFD_HINT": "Age Proof",
    "PFD_FORM_ITEM_TYPE1": "TYPE",
    "PFD_COLUMN_NAME": "PAD_AGE_PROOF_FLAG",
    "PFD_FORM_ITEM_TYPE2": "life_assured_details",
    "PFD_TABLE_NAME": "LT_POL_ASSURED_DET",
    "PFD_DATA_TYPE": "lov",
    "PFD_SYS_ID": 83,
    "PFD_VALIDATION_ID": "1",
    "PFD_MINMAX_YN": false,
    "PFD_FLD_VALUE": "",
    "PFD_DFLT_VALUE_YN": "0",
    "PFD_SEQ_NO": 4,
    "PFD_CLASS_NAME": "CLASS",
    "PFD_VALIDATION_YN": "1",
    "PFD_MANDATORY_YN": true,
    "PFD_EDIT_YN": "1",
    "PFD_FLD_NAME": "AGE PROOF",
    "PFD_RADIO_GRP_NAME": "GROUP",
    "PFD_PROG_CODE": "QUOTATIONENTRY",
    "PFD_FONT_SIZE": "20",
    "PFD_FLD_LEN": "25",
    "PFD_HIDE_YN": "1",
    "PFD_SCREEN_NAME": "QUOTATIONENTRY"
   },
   "PAD_NATURE_OF_WORK": {
    "PFD_HINT": "Nature Of work",
    "PFD_FORM_ITEM_TYPE1": "TYPE",
    "PFD_COLUMN_NAME": "PAD_NATURE_OF_WORK",
    "PFD_FORM_ITEM_TYPE2": "life_assured_details",
    "PFD_TABLE_NAME": "LT_POL_ASSURED_DET",
    "PFD_DATA_TYPE": "text",
    "PFD_SYS_ID": 94,
    "PFD_VALIDATION_ID": "1",
    "PFD_MINMAX_YN": false,
    "PFD_FLD_VALUE": "",
    "PFD_DFLT_VALUE_YN": "0",
    "PFD_SEQ_NO": 15,
    "PFD_CLASS_NAME": "CLASS",
    "PFD_VALIDATION_YN": "1",
    "PFD_MANDATORY_YN": true,
    "PFD_EDIT_YN": "1",
    "PFD_FLD_NAME": "NATURE OF WORK",
    "PFD_RADIO_GRP_NAME": "GROUP",
    "PFD_PROG_CODE": "QUOTATIONENTRY",
    "PFD_FONT_SIZE": "20",
    "PFD_FLD_LEN": "25",
    "PFD_HIDE_YN": "1",
    "PFD_SCREEN_NAME": "QUOTATIONENTRY"
   },
   "PAD_WEIGHT": {
    "PFD_HINT": "Weight",
    "PFD_FORM_ITEM_TYPE1": "TYPE",
    "PFD_COLUMN_NAME": "PAD_WEIGHT",
    "PFD_FORM_ITEM_TYPE2": "life_assured_details",
    "PFD_TABLE_NAME": "LT_POL_ASSURED_DET",
    "PFD_DATA_TYPE": "number",
    "PFD_SYS_ID": 87,
    "PFD_VALIDATION_ID": "1",
    "PFD_MINMAX_YN": false,
    "PFD_FLD_VALUE": "",
    "PFD_DFLT_VALUE_YN": "0",
    "PFD_SEQ_NO": 8,
    "PFD_CLASS_NAME": "CLASS",
    "PFD_VALIDATION_YN": "1",
    "PFD_MANDATORY_YN": true,
    "PFD_EDIT_YN": "1",
    "PFD_FLD_NAME": "WEIGHT",
    "PFD_RADIO_GRP_NAME": "GROUP",
    "PFD_PROG_CODE": "QUOTATIONENTRY",
    "PFD_FONT_SIZE": "20",
    "PFD_FLD_LEN": "25",
    "PFD_HIDE_YN": "1",
    "PFD_SCREEN_NAME": "QUOTATIONENTRY"
   },
   "PAD_BMI": {
    "PFD_HINT": "B.M.I.",
    "PFD_FORM_ITEM_TYPE1": "TYPE",
    "PFD_COLUMN_NAME": "PAD_BMI",
    "PFD_FORM_ITEM_TYPE2": "life_assured_details",
    "PFD_TABLE_NAME": "LT_POL_ASSURED_DET",
    "PFD_DATA_TYPE": "number",
    "PFD_SYS_ID": 88,
    "PFD_VALIDATION_ID": "1",
    "PFD_MINMAX_YN": false,
    "PFD_FLD_VALUE": "",
    "PFD_DFLT_VALUE_YN": "0",
    "PFD_SEQ_NO": 9,
    "PFD_CLASS_NAME": "CLASS",
    "PFD_VALIDATION_YN": "1",
    "PFD_MANDATORY_YN": true,
    "PFD_EDIT_YN": "1",
    "PFD_FLD_NAME": "BMI",
    "PFD_RADIO_GRP_NAME": "GROUP",
    "PFD_PROG_CODE": "QUOTATIONENTRY",
    "PFD_FONT_SIZE": "20",
    "PFD_FLD_LEN": "25",
    "PFD_HIDE_YN": "1",
    "PFD_SCREEN_NAME": "QUOTATIONENTRY"
   },
   "PAD_NATIONALITY": {
    "PFD_HINT": "Nationality",
    "PFD_FORM_ITEM_TYPE1": "TYPE",
    "PFD_COLUMN_NAME": "PAD_NATIONALITY",
    "PFD_FORM_ITEM_TYPE2": "life_assured_details",
    "PFD_TABLE_NAME": "LT_POL_ASSURED_DET",
    "PFD_DATA_TYPE": "codedesc",
    "PFD_SYS_ID": 91,
    "PFD_VALIDATION_ID": "1",
    "PFD_MINMAX_YN": false,
    "PFD_FLD_VALUE": "",
    "PFD_DFLT_VALUE_YN": "0",
    "PFD_SEQ_NO": 12,
    "PFD_CLASS_NAME": "CLASS",
    "PFD_VALIDATION_YN": "1",
    "PFD_MANDATORY_YN": true,
    "PFD_EDIT_YN": "1",
    "PFD_FLD_NAME": "NATIONALITY",
    "PFD_RADIO_GRP_NAME": "GROUP",
    "PFD_PROG_CODE": "QUOTATIONENTRY",
    "PFD_FONT_SIZE": "20",
    "PFD_FLD_LEN": "25",
    "PFD_HIDE_YN": "1",
    "PFD_SCREEN_NAME": "QUOTATIONENTRY"
   },
   "PAD_DOB": {
    "PFD_HINT": "D.O.B.",
    "PFD_FORM_ITEM_TYPE1": "TYPE",
    "PFD_COLUMN_NAME": "PAD_DOB",
    "PFD_FORM_ITEM_TYPE2": "life_assured_details",
    "PFD_TABLE_NAME": "LT_POL_ASSURED_DET",
    "PFD_DATA_TYPE": "date",
    "PFD_SYS_ID": 85,
    "PFD_VALIDATION_ID": "1",
    "PFD_MINMAX_YN": false,
    "PFD_FLD_VALUE": "",
    "PFD_DFLT_VALUE_YN": "0",
    "PFD_SEQ_NO": 6,
    "PFD_CLASS_NAME": "CLASS",
    "PFD_VALIDATION_YN": "1",
    "PFD_MANDATORY_YN": true,
    "PFD_EDIT_YN": "1",
    "PFD_FLD_NAME": "DATE OF BIRTH",
    "PFD_RADIO_GRP_NAME": "GROUP",
    "PFD_PROG_CODE": "QUOTATIONENTRY",
    "PFD_FONT_SIZE": "20",
    "PFD_FLD_LEN": "25",
    "PFD_HIDE_YN": "1",
    "PFD_SCREEN_NAME": "QUOTATIONENTRY"
   },
   "PAD_ASSURED_NAME": {
    "PFD_HINT": "Assured Name",
    "PFD_FORM_ITEM_TYPE1": "",
    "PFD_COLUMN_NAME": "PAD_ASSURED_NAME",
    "PFD_FORM_ITEM_TYPE2": "life_assured_details",
    "PFD_TABLE_NAME": "LT_POL_ASSURED_DET",
    "PFD_DATA_TYPE": "text",
    "PFD_SYS_ID": 80,
    "PFD_VALIDATION_ID": "1",
    "PFD_MINMAX_YN": false,
    "PFD_FLD_VALUE": "",
    "PFD_DFLT_VALUE_YN": "0",
    "PFD_SEQ_NO": 1,
    "PFD_CLASS_NAME": "CLASS",
    "PFD_VALIDATION_YN": "1",
    "PFD_MANDATORY_YN": true,
    "PFD_EDIT_YN": "1",
    "PFD_FLD_NAME": "ASSURED NAME",
    "PFD_RADIO_GRP_NAME": "GROUP",
    "PFD_PROG_CODE": "QUOTATIONENTRY",
    "PFD_FONT_SIZE": "20",
    "PFD_FLD_LEN": "25",
    "PFD_HIDE_YN": "1",
    "PFD_SCREEN_NAME": "QUOTATIONENTRY"
   },
   "PAD_HEIGHT": {
    "PFD_HINT": "Height",
    "PFD_FORM_ITEM_TYPE1": "TYPE",
    "PFD_COLUMN_NAME": "PAD_HEIGHT",
    "PFD_FORM_ITEM_TYPE2": "life_assured_details",
    "PFD_TABLE_NAME": "LT_POL_ASSURED_DET",
    "PFD_DATA_TYPE": "number",
    "PFD_SYS_ID": 86,
    "PFD_VALIDATION_ID": "1",
    "PFD_MINMAX_YN": false,
    "PFD_FLD_VALUE": "",
    "PFD_DFLT_VALUE_YN": "0",
    "PFD_SEQ_NO": 7,
    "PFD_CLASS_NAME": "CLASS",
    "PFD_VALIDATION_YN": "1",
    "PFD_MANDATORY_YN": true,
    "PFD_EDIT_YN": "1",
    "PFD_FLD_NAME": "HEIGHT",
    "PFD_RADIO_GRP_NAME": "GROUP",
    "PFD_PROG_CODE": "QUOTATIONENTRY",
    "PFD_FONT_SIZE": "20",
    "PFD_FLD_LEN": "25",
    "PFD_HIDE_YN": "1",
    "PFD_SCREEN_NAME": "QUOTATIONENTRY"
   },
   "PAD_FC_SUM_ASSURED": {
    "PFD_HINT": "Total Sum Assured",
    "PFD_FORM_ITEM_TYPE1": "TYPE",
    "PFD_COLUMN_NAME": "PAD_FC_SUM_ASSURED",
    "PFD_FORM_ITEM_TYPE2": "life_assured_details",
    "PFD_TABLE_NAME": "LT_POL_ASSURED_DET",
    "PFD_DATA_TYPE": "number",
    "PFD_SYS_ID": 89,
    "PFD_VALIDATION_ID": "1",
    "PFD_MINMAX_YN": false,
    "PFD_FLD_VALUE": "",
    "PFD_DFLT_VALUE_YN": "0",
    "PFD_SEQ_NO": 10,
    "PFD_CLASS_NAME": "CLASS",
    "PFD_VALIDATION_YN": "1",
    "PFD_MANDATORY_YN": true,
    "PFD_EDIT_YN": "1",
    "PFD_FLD_NAME": "TOTAL SUM ASSURED",
    "PFD_RADIO_GRP_NAME": "GROUP",
    "PFD_PROG_CODE": "QUOTATIONENTRY",
    "PFD_FONT_SIZE": "20",
    "PFD_FLD_LEN": "25",
    "PFD_HIDE_YN": "1",
    "PFD_SCREEN_NAME": "QUOTATIONENTRY"
   }
  }
 },
 "frontForm": {
  "Label": "User Entry",
  "formFields": {
   "pol_start_dt": {
    "PFD_HINT": "Start Date",
    "PFD_FORM_ITEM_TYPE1": "FrontFormField",
    "PFD_COLUMN_NAME": "pol_start_dt",
    "PFD_TABLE_NAME": "lt_policy",
    "PFD_DATA_TYPE": "text",
    "PFD_SYS_ID": 70,
    "PFD_VALIDATION_ID": "1",
    "PFD_MINMAX_YN": false,
    "PFD_FLD_VALUE": "",
    "PFD_DFLT_VALUE_YN": "0",
    "PFD_SEQ_NO": 11,
    "PFD_CLASS_NAME": "CLASS",
    "PFD_VALIDATION_YN": "1",
    "PFD_MANDATORY_YN": true,
    "PFD_EDIT_YN": "1",
    "PFD_FLD_NAME": "POLICY START DATE",
    "PFD_RADIO_GRP_NAME": "GROUP",
    "PFD_PROG_CODE": "QUOTATIONENTRY",
    "PFD_FONT_SIZE": "20",
    "PFD_FLD_LEN": "25",
    "PFD_HIDE_YN": "1",
    "PFD_SCREEN_NAME": "QUOTATIONENTRY"
   },
   "PLAN_DESC": {
    "PFD_HINT": "Plan Desc",
    "PFD_FORM_ITEM_TYPE1": "FrontFormField",
    "PFD_COLUMN_NAME": "PLAN_DESC",
    "PFD_TABLE_NAME": "lt_policy",
    "PFD_DATA_TYPE": "text",
    "PFD_SYS_ID": 61,
    "PFD_VALIDATION_ID": "1",
    "PFD_MINMAX_YN": false,
    "PFD_FLD_VALUE": "",
    "PFD_DFLT_VALUE_YN": "0",
    "PFD_SEQ_NO": 2,
    "PFD_CLASS_NAME": "CLASS",
    "PFD_VALIDATION_YN": "1",
    "PFD_MANDATORY_YN": true,
    "PFD_EDIT_YN": "1",
    "PFD_FLD_NAME": "Plan Desc",
    "PFD_RADIO_GRP_NAME": "GROUP",
    "PFD_PROG_CODE": "QUOTATIONENTRY",
    "PFD_FONT_SIZE": "20",
    "PFD_FLD_LEN": "25",
    "PFD_HIDE_YN": "1",
    "PFD_SCREEN_NAME": "QUOTATIONENTRY"
   },
   "POL_FC_ANN_SALARY": {
    "PFD_HINT": "Annual Salary",
    "PFD_FORM_ITEM_TYPE1": "FrontFormField",
    "PFD_COLUMN_NAME": "POL_FC_ANN_SALARY",
    "PFD_TABLE_NAME": "lt_policy",
    "PFD_DATA_TYPE": "text",
    "PFD_SYS_ID": 75,
    "PFD_VALIDATION_ID": "1",
    "PFD_MINMAX_YN": false,
    "PFD_FLD_VALUE": "",
    "PFD_DFLT_VALUE_YN": "0",
    "PFD_SEQ_NO": 16,
    "PFD_CLASS_NAME": "CLASS",
    "PFD_VALIDATION_YN": "1",
    "PFD_MANDATORY_YN": true,
    "PFD_EDIT_YN": "1",
    "PFD_FLD_NAME": "CUSTOMER ANNUAL SALARY",
    "PFD_RADIO_GRP_NAME": "GROUP",
    "PFD_PROG_CODE": "QUOTATIONENTRY",
    "PFD_FONT_SIZE": "20",
    "PFD_FLD_LEN": "25",
    "PFD_HIDE_YN": "1",
    "PFD_SCREEN_NAME": "QUOTATIONENTRY"
   },
   "pol_sa_curr_code": {
    "PFD_HINT": "Currency Code",
    "PFD_FORM_ITEM_TYPE1": "FrontFormField",
    "PFD_COLUMN_NAME": "pol_sa_curr_code",
    "PFD_TABLE_NAME": "lt_policy",
    "PFD_DATA_TYPE": "text",
    "PFD_SYS_ID": 73,
    "PFD_VALIDATION_ID": "1",
    "PFD_MINMAX_YN": false,
    "PFD_FLD_VALUE": "",
    "PFD_DFLT_VALUE_YN": "0",
    "PFD_SEQ_NO": 14,
    "PFD_CLASS_NAME": "CLASS",
    "PFD_VALIDATION_YN": "1",
    "PFD_MANDATORY_YN": true,
    "PFD_EDIT_YN": "1",
    "PFD_FLD_NAME": "POLICY CURRENCY",
    "PFD_RADIO_GRP_NAME": "GROUP",
    "PFD_PROG_CODE": "QUOTATIONENTRY",
    "PFD_FONT_SIZE": "20",
    "PFD_FLD_LEN": "25",
    "PFD_HIDE_YN": "1",
    "PFD_SCREEN_NAME": "QUOTATIONENTRY"
   },
   "pol_last_inst_dt": {
    "PFD_HINT": "Last Installment Date",
    "PFD_FORM_ITEM_TYPE1": "FrontFormField",
    "PFD_COLUMN_NAME": "pol_last_inst_dt",
    "PFD_TABLE_NAME": "lt_policy",
    "PFD_DATA_TYPE": "date",
    "PFD_SYS_ID": 78,
    "PFD_VALIDATION_ID": "1",
    "PFD_MINMAX_YN": false,
    "PFD_FLD_VALUE": "",
    "PFD_DFLT_VALUE_YN": "0",
    "PFD_SEQ_NO": 19,
    "PFD_CLASS_NAME": "CLASS",
    "PFD_VALIDATION_YN": "1",
    "PFD_MANDATORY_YN": true,
    "PFD_EDIT_YN": "1",
    "PFD_FLD_NAME": "LAST INSTALMENT DATE",
    "PFD_RADIO_GRP_NAME": "GROUP",
    "PFD_PROG_CODE": "QUOTATIONENTRY",
    "PFD_FONT_SIZE": "20",
    "PFD_FLD_LEN": "25",
    "PFD_HIDE_YN": "1",
    "PFD_SCREEN_NAME": "QUOTATIONENTRY"
   },
   "pol_mode_of_pymt": {
    "PFD_HINT": "Mode Of Payment",
    "PFD_FORM_ITEM_TYPE1": "FrontFormField",
    "PFD_COLUMN_NAME": "pol_mode_of_pymt",
    "PFD_TABLE_NAME": "lt_policy",
    "PFD_DATA_TYPE": "text",
    "PFD_SYS_ID": 74,
    "PFD_VALIDATION_ID": "1",
    "PFD_MINMAX_YN": false,
    "PFD_FLD_VALUE": "",
    "PFD_DFLT_VALUE_YN": "0",
    "PFD_SEQ_NO": 15,
    "PFD_CLASS_NAME": "CLASS",
    "PFD_VALIDATION_YN": "1",
    "PFD_MANDATORY_YN": true,
    "PFD_EDIT_YN": "1",
    "PFD_FLD_NAME": "MODE OF PAYMENT",
    "PFD_RADIO_GRP_NAME": "GROUP",
    "PFD_PROG_CODE": "QUOTATIONENTRY",
    "PFD_FONT_SIZE": "20",
    "PFD_FLD_LEN": "25",
    "PFD_HIDE_YN": "1",
    "PFD_SCREEN_NAME": "QUOTATIONENTRY"
   },
   "pol_plan_code": {
    "PFD_HINT": "Plan Code",
    "PFD_FORM_ITEM_TYPE1": "FrontFormField",
    "PFD_COLUMN_NAME": "pol_plan_code",
    "PFD_TABLE_NAME": "lt_policy",
    "PFD_DATA_TYPE": "text",
    "PFD_SYS_ID": 60,
    "PFD_VALIDATION_ID": "1",
    "PFD_MINMAX_YN": false,
    "PFD_FLD_VALUE": "",
    "PFD_DFLT_VALUE_YN": "0",
    "PFD_SEQ_NO": 1,
    "PFD_CLASS_NAME": "CLASS",
    "PFD_VALIDATION_YN": "1",
    "PFD_MANDATORY_YN": true,
    "PFD_EDIT_YN": "1",
    "PFD_FLD_NAME": "Plan Code",
    "PFD_RADIO_GRP_NAME": "GROUP",
    "PFD_PROG_CODE": "QUOTATIONENTRY",
    "PFD_FONT_SIZE": "20",
    "PFD_FLD_LEN": "25",
    "PFD_HIDE_YN": "1",
    "PFD_SCREEN_NAME": "QUOTATIONENTRY"
   },
   "pol_src_of_bus": {
    "PFD_HINT": "Source Of Business",
    "PFD_FORM_ITEM_TYPE1": "FrontFormField",
    "PFD_COLUMN_NAME": "pol_src_of_bus",
    "PFD_TABLE_NAME": "lt_policy",
    "PFD_DATA_TYPE": "text",
    "PFD_SYS_ID": 72,
    "PFD_VALIDATION_ID": "1",
    "PFD_MINMAX_YN": false,
    "PFD_FLD_VALUE": "",
    "PFD_DFLT_VALUE_YN": "0",
    "PFD_SEQ_NO": 13,
    "PFD_CLASS_NAME": "CLASS",
    "PFD_VALIDATION_YN": "1",
    "PFD_MANDATORY_YN": true,
    "PFD_EDIT_YN": "1",
    "PFD_FLD_NAME": "SOURCE OF BUSINESS",
    "PFD_RADIO_GRP_NAME": "GROUP",
    "PFD_PROG_CODE": "QUOTATIONENTRY",
    "PFD_FONT_SIZE": "20",
    "PFD_FLD_LEN": "25",
    "PFD_HIDE_YN": "1",
    "PFD_SCREEN_NAME": "QUOTATIONENTRY"
   },
   "pol_fc_sum_assured": {
    "PFD_HINT": "Sum Assured",
    "PFD_FORM_ITEM_TYPE1": "FrontFormField",
    "PFD_COLUMN_NAME": "pol_fc_sum_assured",
    "PFD_TABLE_NAME": "lt_policy",
    "PFD_DATA_TYPE": "number",
    "PFD_SYS_ID": 76,
    "PFD_VALIDATION_ID": "1",
    "PFD_MINMAX_YN": false,
    "PFD_FLD_VALUE": "",
    "PFD_DFLT_VALUE_YN": "0",
    "PFD_SEQ_NO": 17,
    "PFD_CLASS_NAME": "CLASS",
    "PFD_VALIDATION_YN": "1",
    "PFD_MANDATORY_YN": true,
    "PFD_EDIT_YN": "1",
    "PFD_FLD_NAME": "SUM ASSURED",
    "PFD_RADIO_GRP_NAME": "GROUP",
    "PFD_PROG_CODE": "QUOTATIONENTRY",
    "PFD_FONT_SIZE": "20",
    "PFD_FLD_LEN": "25",
    "PFD_HIDE_YN": "1",
    "PFD_SCREEN_NAME": "QUOTATIONENTRY"
   },
   "pol_frz_flag": {
    "PFD_HINT": "Freeze Yn",
    "PFD_FORM_ITEM_TYPE1": "FrontFormField",
    "PFD_COLUMN_NAME": "pol_frz_flag",
    "PFD_TABLE_NAME": "lt_policy",
    "PFD_DATA_TYPE": "text",
    "PFD_SYS_ID": 63,
    "PFD_VALIDATION_ID": "1",
    "PFD_MINMAX_YN": false,
    "PFD_FLD_VALUE": "",
    "PFD_DFLT_VALUE_YN": "0",
    "PFD_SEQ_NO": 4,
    "PFD_CLASS_NAME": "CLASS",
    "PFD_VALIDATION_YN": "1",
    "PFD_MANDATORY_YN": true,
    "PFD_EDIT_YN": "1",
    "PFD_FLD_NAME": "POLICY FREEZE  YN",
    "PFD_RADIO_GRP_NAME": "GROUP",
    "PFD_PROG_CODE": "QUOTATIONENTRY",
    "PFD_FONT_SIZE": "20",
    "PFD_FLD_LEN": "25",
    "PFD_HIDE_YN": "1",
    "PFD_SCREEN_NAME": "QUOTATIONENTRY"
   },
   "pol_uw_year": {
    "PFD_HINT": "UW Year",
    "PFD_FORM_ITEM_TYPE1": "FrontFormField",
    "PFD_COLUMN_NAME": "pol_uw_year",
    "PFD_TABLE_NAME": "lt_policy",
    "PFD_DATA_TYPE": "date",
    "PFD_SYS_ID": 62,
    "PFD_VALIDATION_ID": "1",
    "PFD_MINMAX_YN": false,
    "PFD_FLD_VALUE": "",
    "PFD_DFLT_VALUE_YN": "0",
    "PFD_SEQ_NO": 3,
    "PFD_CLASS_NAME": "CLASS",
    "PFD_VALIDATION_YN": "1",
    "PFD_MANDATORY_YN": true,
    "PFD_EDIT_YN": "1",
    "PFD_FLD_NAME": "Uw Year",
    "PFD_RADIO_GRP_NAME": "GROUP",
    "PFD_PROG_CODE": "QUOTATIONENTRY",
    "PFD_FONT_SIZE": "20",
    "PFD_FLD_LEN": "25",
    "PFD_HIDE_YN": "1",
    "PFD_SCREEN_NAME": "QUOTATIONENTRY"
   },
   "pol_cust_code": {
    "PFD_HINT": "Customer Code-Customer Name",
    "PFD_FORM_ITEM_TYPE1": "FrontFormField",
    "PFD_COLUMN_NAME": "pol_cust_code",
    "PFD_TABLE_NAME": "lt_policy",
    "PFD_DATA_TYPE": "codedesc",
    "PFD_SYS_ID": 65,
    "PFD_PARAM_1": "31",
    "PFD_VALIDATION_ID": "1",
    "PFD_MINMAX_YN": false,
    "PFD_FLD_VALUE": "",
    "PFD_DFLT_VALUE_YN": "0",
    "PFD_SEQ_NO": 6,
    "PFD_CLASS_NAME": "CLASS",
    "PFD_VALIDATION_YN": "1",
    "PFD_MANDATORY_YN": true,
    "PFD_EDIT_YN": "1",
    "PFD_FLD_NAME": "CUSTOMER CODE",
    "PFD_RADIO_GRP_NAME": "GROUP",
    "PFD_PROG_CODE": "QUOTATIONENTRY",
    "PFD_FONT_SIZE": "20",
    "PFD_FLD_LEN": "25",
    "PFD_HIDE_YN": "1",
    "PFD_SCREEN_NAME": "QUOTATIONENTRY"
   },
   "pol_first_inst_dt": {
    "PFD_HINT": "First Installment Date",
    "PFD_FORM_ITEM_TYPE1": "FrontFormField",
    "PFD_COLUMN_NAME": "pol_first_inst_dt",
    "PFD_TABLE_NAME": "lt_policy",
    "PFD_DATA_TYPE": "date",
    "PFD_SYS_ID": 77,
    "PFD_VALIDATION_ID": "1",
    "PFD_MINMAX_YN": false,
    "PFD_FLD_VALUE": "",
    "PFD_DFLT_VALUE_YN": "0",
    "PFD_SEQ_NO": 18,
    "PFD_CLASS_NAME": "CLASS",
    "PFD_VALIDATION_YN": "1",
    "PFD_MANDATORY_YN": true,
    "PFD_EDIT_YN": "1",
    "PFD_FLD_NAME": "FIRST INSTALLMENT DATE",
    "PFD_RADIO_GRP_NAME": "GROUP",
    "PFD_PROG_CODE": "QUOTATIONENTRY",
    "PFD_FONT_SIZE": "20",
    "PFD_FLD_LEN": "25",
    "PFD_HIDE_YN": "1",
    "PFD_SCREEN_NAME": "QUOTATIONENTRY"
   }
  }
 },
 "Charges": {
  "Label": "Charges",
  "formFields": {
   "POC_RATE_PER": {
    "PFD_HINT": "Rate Per",
    "PFD_FORM_ITEM_TYPE1": "TYPE",
    "PFD_COLUMN_NAME": "POC_RATE_PER",
    "PFD_FORM_ITEM_TYPE2": "Charges",
    "PFD_TABLE_NAME": "LT_POL_CHARGE",
    "PFD_DATA_TYPE": "text",
    "PFD_SYS_ID": 98,
    "PFD_VALIDATION_ID": "1",
    "PFD_MINMAX_YN": false,
    "PFD_FLD_VALUE": "",
    "PFD_DFLT_VALUE_YN": "0",
    "PFD_SEQ_NO": 4,
    "PFD_CLASS_NAME": "CLASS",
    "PFD_VALIDATION_YN": "1",
    "PFD_MANDATORY_YN": true,
    "PFD_EDIT_YN": "1",
    "PFD_FLD_NAME": "RATE PER",
    "PFD_RADIO_GRP_NAME": "GROUP",
    "PFD_PROG_CODE": "QUOTATIONENTRY",
    "PFD_FONT_SIZE": "20",
    "PFD_FLD_LEN": "25",
    "PFD_HIDE_YN": "1",
    "PFD_SCREEN_NAME": "QUOTATIONENTRY"
   },
   "POC_APPLY_PERIOD": {
    "PFD_HINT": "Charges Apply Period",
    "PFD_FORM_ITEM_TYPE1": "TYPE",
    "PFD_COLUMN_NAME": "POC_APPLY_PERIOD",
    "PFD_FORM_ITEM_TYPE2": "Charges",
    "PFD_TABLE_NAME": "LT_POL_CHARGE",
    "PFD_DATA_TYPE": "text",
    "PFD_SYS_ID": 99,
    "PFD_VALIDATION_ID": "1",
    "PFD_MINMAX_YN": false,
    "PFD_FLD_VALUE": "",
    "PFD_DFLT_VALUE_YN": "0",
    "PFD_SEQ_NO": 5,
    "PFD_CLASS_NAME": "CLASS",
    "PFD_VALIDATION_YN": "1",
    "PFD_MANDATORY_YN": true,
    "PFD_EDIT_YN": "1",
    "PFD_FLD_NAME": "CHARGES APPLY PERIOD",
    "PFD_RADIO_GRP_NAME": "GROUP",
    "PFD_PROG_CODE": "QUOTATIONENTRY",
    "PFD_FONT_SIZE": "20",
    "PFD_FLD_LEN": "25",
    "PFD_HIDE_YN": "1",
    "PFD_SCREEN_NAME": "QUOTATIONENTRY"
   },
   "POC_CHRG_CODE": {
    "PFD_HINT": "Charge Code",
    "PFD_FORM_ITEM_TYPE1": "TYPE",
    "PFD_COLUMN_NAME": "POC_CHRG_CODE",
    "PFD_FORM_ITEM_TYPE2": "Charges",
    "PFD_TABLE_NAME": "LT_POL_CHARGE",
    "PFD_DATA_TYPE": "text",
    "PFD_SYS_ID": 95,
    "PFD_VALIDATION_ID": "1",
    "PFD_MINMAX_YN": false,
    "PFD_FLD_VALUE": "",
    "PFD_DFLT_VALUE_YN": "0",
    "PFD_SEQ_NO": 1,
    "PFD_CLASS_NAME": "CLASS",
    "PFD_VALIDATION_YN": "1",
    "PFD_MANDATORY_YN": true,
    "PFD_EDIT_YN": "1",
    "PFD_FLD_NAME": "CHARGE CODE",
    "PFD_RADIO_GRP_NAME": "GROUP",
    "PFD_PROG_CODE": "QUOTATIONENTRY",
    "PFD_FONT_SIZE": "20",
    "PFD_FLD_LEN": "25",
    "PFD_HIDE_YN": "1",
    "PFD_SCREEN_NAME": "QUOTATIONENTRY"
   },
   "POC_CHRG_VALUE": {
    "PFD_HINT": "Charge Value",
    "PFD_FORM_ITEM_TYPE1": "TYPE",
    "PFD_COLUMN_NAME": "POC_CHRG_VALUE",
    "PFD_FORM_ITEM_TYPE2": "Charges",
    "PFD_TABLE_NAME": "LT_POL_CHARGE",
    "PFD_DATA_TYPE": "text",
    "PFD_SYS_ID": 100,
    "PFD_VALIDATION_ID": "1",
    "PFD_MINMAX_YN": false,
    "PFD_FLD_VALUE": "",
    "PFD_DFLT_VALUE_YN": "0",
    "PFD_SEQ_NO": 6,
    "PFD_CLASS_NAME": "CLASS",
    "PFD_VALIDATION_YN": "1",
    "PFD_MANDATORY_YN": true,
    "PFD_EDIT_YN": "1",
    "PFD_FLD_NAME": "CHARGE VALUE",
    "PFD_RADIO_GRP_NAME": "GROUP",
    "PFD_PROG_CODE": "QUOTATIONENTRY",
    "PFD_FONT_SIZE": "20",
    "PFD_FLD_LEN": "25",
    "PFD_HIDE_YN": "1",
    "PFD_SCREEN_NAME": "QUOTATIONENTRY"
   },
   "POC_RATE": {
    "PFD_HINT": "Rate",
    "PFD_FORM_ITEM_TYPE1": "TYPE",
    "PFD_COLUMN_NAME": "POC_RATE",
    "PFD_FORM_ITEM_TYPE2": "Charges",
    "PFD_TABLE_NAME": "LT_POL_CHARGE",
    "PFD_DATA_TYPE": "text",
    "PFD_SYS_ID": 97,
    "PFD_VALIDATION_ID": "1",
    "PFD_MINMAX_YN": false,
    "PFD_FLD_VALUE": "",
    "PFD_DFLT_VALUE_YN": "0",
    "PFD_SEQ_NO": 3,
    "PFD_CLASS_NAME": "CLASS",
    "PFD_VALIDATION_YN": "1",
    "PFD_MANDATORY_YN": true,
    "PFD_EDIT_YN": "1",
    "PFD_FLD_NAME": "RATE ",
    "PFD_RADIO_GRP_NAME": "GROUP",
    "PFD_PROG_CODE": "QUOTATIONENTRY",
    "PFD_FONT_SIZE": "20",
    "PFD_FLD_LEN": "25",
    "PFD_HIDE_YN": "1",
    "PFD_SCREEN_NAME": "QUOTATIONENTRY"
   },
   "POC_APPLIED_ON": {
    "PFD_HINT": "Charge Applied On",
    "PFD_FORM_ITEM_TYPE1": "TYPE",
    "PFD_COLUMN_NAME": "POC_APPLIED_ON",
    "PFD_FORM_ITEM_TYPE2": "Charges",
    "PFD_TABLE_NAME": "LT_POL_CHARGE",
    "PFD_DATA_TYPE": "text",
    "PFD_SYS_ID": 96,
    "PFD_VALIDATION_ID": "1",
    "PFD_MINMAX_YN": false,
    "PFD_FLD_VALUE": "",
    "PFD_DFLT_VALUE_YN": "0",
    "PFD_SEQ_NO": 2,
    "PFD_CLASS_NAME": "CLASS",
    "PFD_VALIDATION_YN": "1",
    "PFD_MANDATORY_YN": true,
    "PFD_EDIT_YN": "1",
    "PFD_FLD_NAME": "CHARGE APPLIED ON",
    "PFD_RADIO_GRP_NAME": "GROUP",
    "PFD_PROG_CODE": "QUOTATIONENTRY",
    "PFD_FONT_SIZE": "20",
    "PFD_FLD_LEN": "25",
    "PFD_HIDE_YN": "1",
    "PFD_SCREEN_NAME": "QUOTATIONENTRY"
   }
  }
 },
 "checklist": {
  "Label": "checklist",
  "formFields": {
   "DTLS_SR_NO": {
    "PFD_HINT": "Sr.No",
    "PFD_FORM_ITEM_TYPE1": "TYPE",
    "PFD_COLUMN_NAME": "DTLS_SR_NO",
    "PFD_FORM_ITEM_TYPE2": "checklist",
    "PFD_TABLE_NAME": "LT_DOC_TODO_LIST_STATUS",
    "PFD_DATA_TYPE": "number",
    "PFD_SYS_ID": 354,
    "PFD_VALIDATION_ID": "1",
    "PFD_MINMAX_YN": false,
    "PFD_FLD_VALUE": "",
    "PFD_SEQ_NO": 1,
    "PFD_CLASS_NAME": "CLASS",
    "PFD_VALIDATION_YN": "1",
    "PFD_MANDATORY_YN": true,
    "PFD_EDIT_YN": "1",
    "PFD_FLD_NAME": "SERIAL NO",
    "PFD_RADIO_GRP_NAME": "GROUP",
    "PFD_PROG_CODE": "QUOTATIONENTRY",
    "PFD_FONT_SIZE": "20",
    "PFD_FLD_LEN": "25",
    "PFD_HIDE_YN": "1",
    "PFD_SCREEN_NAME": "QUOTATIONENTRY"
   },
   "DTLS_APPR_STS": {
    "PFD_HINT": "Mandatory YN",
    "PFD_FORM_ITEM_TYPE1": "TYPE",
    "PFD_COLUMN_NAME": "DTLS_APPR_STS",
    "PFD_FORM_ITEM_TYPE2": "checklist",
    "PFD_TABLE_NAME": "LT_DOC_TODO_LIST_STATUS",
    "PFD_DATA_TYPE": "text",
    "PFD_SYS_ID": 357,
    "PFD_VALIDATION_ID": "1",
    "PFD_MINMAX_YN": false,
    "PFD_FLD_VALUE": "",
    "PFD_SEQ_NO": 4,
    "PFD_CLASS_NAME": "CLASS",
    "PFD_VALIDATION_YN": "1",
    "PFD_MANDATORY_YN": true,
    "PFD_EDIT_YN": "1",
    "PFD_FLD_NAME": "MANDATORY YN",
    "PFD_RADIO_GRP_NAME": "GROUP",
    "PFD_PROG_CODE": "QUOTATIONENTRY",
    "PFD_FONT_SIZE": "20",
    "PFD_FLD_LEN": "25",
    "PFD_HIDE_YN": "1",
    "PFD_SCREEN_NAME": "QUOTATIONENTRY"
   },
   "DTLS_MANDATORY_YN": {
    "PFD_HINT": "Received YN",
    "PFD_FORM_ITEM_TYPE1": "TYPE",
    "PFD_COLUMN_NAME": "DTLS_MANDATORY_YN",
    "PFD_FORM_ITEM_TYPE2": "checklist",
    "PFD_TABLE_NAME": "LT_DOC_TODO_LIST_STATUS",
    "PFD_DATA_TYPE": "text",
    "PFD_SYS_ID": 356,
    "PFD_VALIDATION_ID": "1",
    "PFD_MINMAX_YN": false,
    "PFD_FLD_VALUE": "",
    "PFD_SEQ_NO": 3,
    "PFD_CLASS_NAME": "CLASS",
    "PFD_VALIDATION_YN": "1",
    "PFD_MANDATORY_YN": true,
    "PFD_EDIT_YN": "1",
    "PFD_FLD_NAME": "RECEIVED YN",
    "PFD_RADIO_GRP_NAME": "GROUP",
    "PFD_PROG_CODE": "QUOTATIONENTRY",
    "PFD_FONT_SIZE": "20",
    "PFD_FLD_LEN": "25",
    "PFD_HIDE_YN": "1",
    "PFD_SCREEN_NAME": "QUOTATIONENTRY"
   },
   "DTLS_TODO_LIST_ITEM": {
    "PFD_HINT": "List Item Desc",
    "PFD_FORM_ITEM_TYPE1": "TYPE",
    "PFD_COLUMN_NAME": "DTLS_TODO_LIST_ITEM",
    "PFD_FORM_ITEM_TYPE2": "checklist",
    "PFD_TABLE_NAME": "LT_DOC_TODO_LIST_STATUS",
    "PFD_DATA_TYPE": "text",
    "PFD_SYS_ID": 355,
    "PFD_VALIDATION_ID": "1",
    "PFD_MINMAX_YN": false,
    "PFD_FLD_VALUE": "",
    "PFD_SEQ_NO": 2,
    "PFD_CLASS_NAME": "CLASS",
    "PFD_VALIDATION_YN": "1",
    "PFD_MANDATORY_YN": true,
    "PFD_EDIT_YN": "1",
    "PFD_FLD_NAME": "LIST ITEM DESC",
    "PFD_RADIO_GRP_NAME": "GROUP",
    "PFD_PROG_CODE": "QUOTATIONENTRY",
    "PFD_FONT_SIZE": "20",
    "PFD_FLD_LEN": "25",
    "PFD_HIDE_YN": "1",
    "PFD_SCREEN_NAME": "QUOTATIONENTRY"
   }
  }
 },
 "charges_dis_load_conditions": {
  "Label": "charges_dis_load_conditions",
  "formFields": {}
 },
 "cmts_mat_remindr": { "Label": "cmts_mat_remindr", "formFields": {} },
 "Conditions": { "Label": "Conditions", "formFields": {} },
 "Discount_Loading": {
  "Label": "Discount_Loading",
  "formFields": {
   "PD_COVER_CODE": {
    "PFD_HINT": "Cover Code",
    "PFD_FORM_ITEM_TYPE1": "TYPE",
    "PFD_COLUMN_NAME": "PD_COVER_CODE",
    "PFD_FORM_ITEM_TYPE2": "Discount_Loading",
    "PFD_TABLE_NAME": "LT_POL_DISC_LOAD",
    "PFD_DATA_TYPE": "text",
    "PFD_SYS_ID": 104,
    "PFD_VALIDATION_ID": "1",
    "PFD_MINMAX_YN": false,
    "PFD_FLD_VALUE": "",
    "PFD_DFLT_VALUE_YN": "0",
    "PFD_SEQ_NO": 4,
    "PFD_CLASS_NAME": "CLASS",
    "PFD_VALIDATION_YN": "1",
    "PFD_MANDATORY_YN": true,
    "PFD_EDIT_YN": "1",
    "PFD_FLD_NAME": "COVER CODE",
    "PFD_RADIO_GRP_NAME": "GROUP",
    "PFD_PROG_CODE": "QUOTATIONENTRY",
    "PFD_FONT_SIZE": "20",
    "PFD_FLD_LEN": "25",
    "PFD_HIDE_YN": "1",
    "PFD_SCREEN_NAME": "QUOTATIONENTRY"
   },
   "PD_APPLIED_ON": {
    "PFD_HINT": "Applied On",
    "PFD_FORM_ITEM_TYPE1": "TYPE",
    "PFD_COLUMN_NAME": "PD_APPLIED_ON",
    "PFD_FORM_ITEM_TYPE2": "Discount_Loading",
    "PFD_TABLE_NAME": "LT_POL_DISC_LOAD",
    "PFD_DATA_TYPE": "text",
    "PFD_SYS_ID": 103,
    "PFD_VALIDATION_ID": "1",
    "PFD_MINMAX_YN": false,
    "PFD_FLD_VALUE": "",
    "PFD_DFLT_VALUE_YN": "0",
    "PFD_SEQ_NO": 3,
    "PFD_CLASS_NAME": "CLASS",
    "PFD_VALIDATION_YN": "1",
    "PFD_MANDATORY_YN": true,
    "PFD_EDIT_YN": "1",
    "PFD_FLD_NAME": "APPLIED ON",
    "PFD_RADIO_GRP_NAME": "GROUP",
    "PFD_PROG_CODE": "QUOTATIONENTRY",
    "PFD_FONT_SIZE": "20",
    "PFD_FLD_LEN": "25",
    "PFD_HIDE_YN": "1",
    "PFD_SCREEN_NAME": "QUOTATIONENTRY"
   },
   "PD_DISC_LOAD_CODE": {
    "PFD_HINT": "Code|Desc",
    "PFD_FORM_ITEM_TYPE1": "TYPE",
    "PFD_COLUMN_NAME": "PD_DISC_LOAD_CODE",
    "PFD_FORM_ITEM_TYPE2": "Discount_Loading",
    "PFD_TABLE_NAME": "LT_POL_DISC_LOAD",
    "PFD_DATA_TYPE": "text",
    "PFD_SYS_ID": 102,
    "PFD_VALIDATION_ID": "1",
    "PFD_MINMAX_YN": false,
    "PFD_FLD_VALUE": "",
    "PFD_DFLT_VALUE_YN": "0",
    "PFD_SEQ_NO": 2,
    "PFD_CLASS_NAME": "CLASS",
    "PFD_VALIDATION_YN": "1",
    "PFD_MANDATORY_YN": true,
    "PFD_EDIT_YN": "1",
    "PFD_FLD_NAME": "CODE AND DESC",
    "PFD_RADIO_GRP_NAME": "GROUP",
    "PFD_PROG_CODE": "QUOTATIONENTRY",
    "PFD_FONT_SIZE": "20",
    "PFD_FLD_LEN": "25",
    "PFD_HIDE_YN": "1",
    "PFD_SCREEN_NAME": "QUOTATIONENTRY"
   },
   "PD_RATE": {
    "PFD_HINT": "Rate",
    "PFD_FORM_ITEM_TYPE1": "TYPE",
    "PFD_COLUMN_NAME": "PD_RATE",
    "PFD_FORM_ITEM_TYPE2": "Discount_Loading",
    "PFD_TABLE_NAME": "LT_POL_DISC_LOAD",
    "PFD_DATA_TYPE": "text",
    "PFD_SYS_ID": 105,
    "PFD_VALIDATION_ID": "1",
    "PFD_MINMAX_YN": false,
    "PFD_FLD_VALUE": "",
    "PFD_DFLT_VALUE_YN": "0",
    "PFD_SEQ_NO": 5,
    "PFD_CLASS_NAME": "CLASS",
    "PFD_VALIDATION_YN": "1",
    "PFD_MANDATORY_YN": true,
    "PFD_EDIT_YN": "1",
    "PFD_FLD_NAME": "RATE ",
    "PFD_RADIO_GRP_NAME": "GROUP",
    "PFD_PROG_CODE": "QUOTATIONENTRY",
    "PFD_FONT_SIZE": "20",
    "PFD_FLD_LEN": "25",
    "PFD_HIDE_YN": "1",
    "PFD_SCREEN_NAME": "QUOTATIONENTRY"
   },
   "PD_FC_DISC_LOAD_VALUE": {
    "PFD_HINT": "Loading/Discount Value",
    "PFD_FORM_ITEM_TYPE1": "TYPE",
    "PFD_COLUMN_NAME": "PD_FC_DISC_LOAD_VALUE",
    "PFD_FORM_ITEM_TYPE2": "Discount_Loading",
    "PFD_TABLE_NAME": "LT_POL_DISC_LOAD",
    "PFD_DATA_TYPE": "text",
    "PFD_SYS_ID": 107,
    "PFD_VALIDATION_ID": "1",
    "PFD_MINMAX_YN": false,
    "PFD_FLD_VALUE": "",
    "PFD_DFLT_VALUE_YN": "0",
    "PFD_SEQ_NO": 7,
    "PFD_CLASS_NAME": "CLASS",
    "PFD_VALIDATION_YN": "1",
    "PFD_MANDATORY_YN": true,
    "PFD_EDIT_YN": "1",
    "PFD_FLD_NAME": "LOADING/DISCOUNT VALUE",
    "PFD_RADIO_GRP_NAME": "GROUP",
    "PFD_PROG_CODE": "QUOTATIONENTRY",
    "PFD_FONT_SIZE": "20",
    "PFD_FLD_LEN": "25",
    "PFD_HIDE_YN": "1",
    "PFD_SCREEN_NAME": "QUOTATIONENTRY"
   },
   "PD_RATE_PER": {
    "PFD_HINT": "Rate Per",
    "PFD_FORM_ITEM_TYPE1": "TYPE",
    "PFD_COLUMN_NAME": "PD_RATE_PER",
    "PFD_FORM_ITEM_TYPE2": "Discount_Loading",
    "PFD_TABLE_NAME": "LT_POL_DISC_LOAD",
    "PFD_DATA_TYPE": "text",
    "PFD_SYS_ID": 106,
    "PFD_VALIDATION_ID": "1",
    "PFD_MINMAX_YN": false,
    "PFD_FLD_VALUE": "",
    "PFD_DFLT_VALUE_YN": "0",
    "PFD_SEQ_NO": 6,
    "PFD_CLASS_NAME": "CLASS",
    "PFD_VALIDATION_YN": "1",
    "PFD_MANDATORY_YN": true,
    "PFD_EDIT_YN": "1",
    "PFD_FLD_NAME": "RATE PER",
    "PFD_RADIO_GRP_NAME": "GROUP",
    "PFD_PROG_CODE": "QUOTATIONENTRY",
    "PFD_FONT_SIZE": "20",
    "PFD_FLD_LEN": "25",
    "PFD_HIDE_YN": "1",
    "PFD_SCREEN_NAME": "QUOTATIONENTRY"
   },
   "PD_DISC_LOAD_TYPE": {
    "PFD_HINT": "Loading/ Discount",
    "PFD_FORM_ITEM_TYPE1": "TYPE",
    "PFD_COLUMN_NAME": "PD_DISC_LOAD_TYPE",
    "PFD_FORM_ITEM_TYPE2": "Discount_Loading",
    "PFD_TABLE_NAME": "LT_POL_DISC_LOAD",
    "PFD_DATA_TYPE": "text",
    "PFD_SYS_ID": 101,
    "PFD_VALIDATION_ID": "1",
    "PFD_MINMAX_YN": false,
    "PFD_FLD_VALUE": "",
    "PFD_DFLT_VALUE_YN": "0",
    "PFD_SEQ_NO": 1,
    "PFD_CLASS_NAME": "CLASS",
    "PFD_VALIDATION_YN": "1",
    "PFD_MANDATORY_YN": true,
    "PFD_EDIT_YN": "1",
    "PFD_FLD_NAME": "LOADING/ DISCOUNT",
    "PFD_RADIO_GRP_NAME": "GROUP",
    "PFD_PROG_CODE": "QUOTATIONENTRY",
    "PFD_FONT_SIZE": "20",
    "PFD_FLD_LEN": "25",
    "PFD_HIDE_YN": "1",
    "PFD_SCREEN_NAME": "QUOTATIONENTRY"
   }
  }
 }
}
